sentrylog/README.md
sentrylog/__init__.py
sentrylog/config.py
sentrylog/log_test.py
sentrylog/logger.py
sentrylog/requirements.txt
sentrylog-0.0.3.dist-info/METADATA
sentrylog-0.0.3.dist-info/WHEEL
sentrylog-0.0.3.dist-info/top_level.txt
sentrylog-0.0.3.dist-info/RECORD
