Metadata-Version: 2.1
Name: sentrylog
Version: 0.0.3
Summary: sentry-logging
Home-page: https://gitee.com/zhangyaoo/sentrylogging
Author: Zack
Author-email: 1125564921@qq.com
License: UNKNOWN
Platform: UNKNOWN
Classifier: Programming Language :: Python :: 3
Classifier: License :: OSI Approved :: MIT License
Classifier: Operating System :: OS Independent
Classifier: Topic :: System :: Logging
